exovista/__init__.py
exovista/allclose.py
exovista/config.py
exovista/copy.py
exovista/element.py
exovista/ex_params.py
exovista/exodus_h.py
exovista/exoread.py
exovista/extension.py
exovista/file.py
exovista/find_in_region.py
exovista/lineout.py
exovista/nc.py
exovista/netcdf.py
exovista/parallel_file.py
exovista/put_solution.py
exovista/region.py
exovista/similar.py
exovista/util.py
exovista/write_pyvista.py
exovista-1.0.9.dist-info/licenses/LICENSE
exovista-1.0.9.dist-info/METADATA
exovista-1.0.9.dist-info/WHEEL
exovista-1.0.9.dist-info/entry_points.txt
exovista-1.0.9.dist-info/top_level.txt
exovista-1.0.9.dist-info/RECORD
