Metadata-Version: 2.4
Name: exovista
Version: 1.0.9
Summary: Python wrappers to the ExodusII finite element database model
License-File: LICENSE
Requires-Dist: netcdf4
Requires-Dist: pyvista
Requires-Dist: numpy
Requires-Dist: scipy
Dynamic: license-file
